{
  "project_info": {
    "project_number": "286526136307",
    "project_id": "wordix-kp",
    "storage_bucket": "wordix-kp.firebasestorage.app"
  },
  "client": [
    {
      "client_info": {
        "mobilesdk_app_id": "1:286526136307:android:d535f6e96e06bbabd97c86",
        "android_client_info": {
          "package_name": "com.example.wordlegame"
        }
      },
      "oauth_client": [],
      "api_key": [
        {
          "current_key": "AIzaSyDNNCeJiuZmoncLZOx53b3-UgHcuLhkmFE"
        }
      ],
      "services": {
        "appinvite_service": {
          "other_platform_oauth_client": []
        }
      }
    }
  ],
  "configuration_version": "1"
}